setup.py
ymci_ext_acl/__init__.py
ymci_ext_acl/db.py
ymci_ext_acl/form.py
ymci_ext_acl/hooks.py
ymci_ext_acl/routes.py
ymci_ext_acl/validators.py
ymci_ext_acl.egg-info/PKG-INFO
ymci_ext_acl.egg-info/SOURCES.txt
ymci_ext_acl.egg-info/dependency_links.txt
ymci_ext_acl.egg-info/entry_points.txt
ymci_ext_acl.egg-info/top_level.txt
ymci_ext_acl/templates/blocks
ymci_ext_acl/templates/index.html