Metadata-Version: 1.1
Name: ymci-ext-acl
Version: 1.1
Summary: ACL rights plugin for ymci
Home-page: UNKNOWN
Author: Jean-Marc Martins, Kozea
Author-email: jmartins@kozea.fr
License: UNKNOWN
Platform: Any
Provides: ymci_ext_acl
